textembedding/__init__.py
textembedding/get_embedding/__init__.py
textembedding/get_embedding/pos_tags.txt
textembedding/get_embedding/sentence_embedding.py
textembedding/get_embedding/similarity.py
textembedding/get_embedding/stop_words.txt
textembedding/get_embedding/utils.py
textembedding/get_embedding/word_embedding.py
textembedding/load_model/__init__.py
textembedding/load_model/load_worc2vect.py
textembedding-1.0.4.dist-info/LICENSE
textembedding-1.0.4.dist-info/METADATA
textembedding-1.0.4.dist-info/WHEEL
textembedding-1.0.4.dist-info/top_level.txt
textembedding-1.0.4.dist-info/RECORD
