Metadata-Version: 2.1
Name: textembedding
Version: 1.0.4
Summary: a library that get text embeddings
Home-page: https://github.com/Hanscal/textembedding
Author: hanscal
Author-email: hanscalcai@163.com
License: UNKNOWN
Platform: UNKNOWN
Classifier: Programming Language :: Python :: 3
Classifier: License :: OSI Approved :: MIT License
Classifier: Operating System :: OS Independent
